[
    {
      "inputs": [
        {
          "internalType": "bytes32",
          "name": "genesisValidatorsRoot",
          "type": "bytes32"
        },
        {
          "internalType": "uint256",
          "name": "genesisTime",
          "type": "uint256"
        },
        {
          "internalType": "uint256",
          "name": "secondsPerSlot",
          "type": "uint256"
        },
        {
          "internalType": "uint256",
          "name": "slotsPerPeriod",
          "type": "uint256"
        },
        {
          "internalType": "uint256",
          "name": "syncCommitteePeriod",
          "type": "uint256"
        },
        {
          "internalType": "bytes32",
          "name": "syncCommitteePoseidon",
          "type": "bytes32"
        },
        {
          "internalType": "uint32",
          "name": "sourceChainId",
          "type": "uint32"
        },
        {
          "internalType": "uint16",
          "name": "finalityThreshold",
          "type": "uint16"
        }
      ],
      "stateMutability": "nonpayable",
      "type": "constructor"
    },
    {
      "anonymous": false,
      "inputs": [
        {
          "indexed": true,
          "internalType": "uint256",
          "name": "slot",
          "type": "uint256"
        },
        {
          "indexed": true,
          "internalType": "bytes32",
          "name": "root",
          "type": "bytes32"
        }
      ],
      "name": "HeadUpdate",
      "type": "event"
    },
    {
      "anonymous": false,
      "inputs": [
        {
          "indexed": true,
          "internalType": "uint256",
          "name": "period",
          "type": "uint256"
        },
        {
          "indexed": true,
          "internalType": "bytes32",
          "name": "root",
          "type": "bytes32"
        }
      ],
      "name": "SyncCommitteeUpdate",
      "type": "event"
    },
    {
      "inputs": [],
      "name": "FINALITY_THRESHOLD",
      "outputs": [
        {
          "internalType": "uint16",
          "name": "",
          "type": "uint16"
        }
      ],
      "stateMutability": "view",
      "type": "function"
    },
    {
      "inputs": [],
      "name": "GENESIS_TIME",
      "outputs": [
        {
          "internalType": "uint256",
          "name": "",
          "type": "uint256"
        }
      ],
      "stateMutability": "view",
      "type": "function"
    },
    {
      "inputs": [],
      "name": "GENESIS_VALIDATORS_ROOT",
      "outputs": [
        {
          "internalType": "bytes32",
          "name": "",
          "type": "bytes32"
        }
      ],
      "stateMutability": "view",
      "type": "function"
    },
    {
      "inputs": [],
      "name": "SECONDS_PER_SLOT",
      "outputs": [
        {
          "internalType": "uint256",
          "name": "",
          "type": "uint256"
        }
      ],
      "stateMutability": "view",
      "type": "function"
    },
    {
      "inputs": [],
      "name": "SLOTS_PER_PERIOD",
      "outputs": [
        {
          "internalType": "uint256",
          "name": "",
          "type": "uint256"
        }
      ],
      "stateMutability": "view",
      "type": "function"
    },
    {
      "inputs": [],
      "name": "SOURCE_CHAIN_ID",
      "outputs": [
        {
          "internalType": "uint32",
          "name": "",
          "type": "uint32"
        }
      ],
      "stateMutability": "view",
      "type": "function"
    },
    {
      "inputs": [],
      "name": "consistent",
      "outputs": [
        {
          "internalType": "bool",
          "name": "",
          "type": "bool"
        }
      ],
      "stateMutability": "view",
      "type": "function"
    },
    {
      "inputs": [
        {
          "internalType": "uint256",
          "name": "",
          "type": "uint256"
        }
      ],
      "name": "executionStateRoots",
      "outputs": [
        {
          "internalType": "bytes32",
          "name": "",
          "type": "bytes32"
        }
      ],
      "stateMutability": "view",
      "type": "function"
    },
    {
      "inputs": [],
      "name": "head",
      "outputs": [
        {
          "internalType": "uint256",
          "name": "",
          "type": "uint256"
        }
      ],
      "stateMutability": "view",
      "type": "function"
    },
    {
      "inputs": [
        {
          "internalType": "uint256",
          "name": "",
          "type": "uint256"
        }
      ],
      "name": "headers",
      "outputs": [
        {
          "internalType": "bytes32",
          "name": "",
          "type": "bytes32"
        }
      ],
      "stateMutability": "view",
      "type": "function"
    },
    {
      "inputs": [
        {
          "components": [
            {
              "components": [
                {
                  "internalType": "uint256",
                  "name": "attestedSlot",
                  "type": "uint256"
                },
                {
                  "internalType": "uint256",
                  "name": "finalizedSlot",
                  "type": "uint256"
                },
                {
                  "internalType": "uint256",
                  "name": "participation",
                  "type": "uint256"
                },
                {
                  "internalType": "bytes32",
                  "name": "finalizedHeaderRoot",
                  "type": "bytes32"
                },
                {
                  "internalType": "bytes32",
                  "name": "executionStateRoot",
                  "type": "bytes32"
                },
                {
                  "components": [
                    {
                      "internalType": "uint256[2]",
                      "name": "a",
                      "type": "uint256[2]"
                    },
                    {
                      "internalType": "uint256[2][2]",
                      "name": "b",
                      "type": "uint256[2][2]"
                    },
                    {
                      "internalType": "uint256[2]",
                      "name": "c",
                      "type": "uint256[2]"
                    }
                  ],
                  "internalType": "struct Groth16Proof",
                  "name": "proof",
                  "type": "tuple"
                }
              ],
              "internalType": "struct LightClientStep",
              "name": "step",
              "type": "tuple"
            },
            {
              "internalType": "bytes32",
              "name": "syncCommitteeSSZ",
              "type": "bytes32"
            },
            {
              "internalType": "bytes32",
              "name": "syncCommitteePoseidon",
              "type": "bytes32"
            },
            {
              "components": [
                {
                  "internalType": "uint256[2]",
                  "name": "a",
                  "type": "uint256[2]"
                },
                {
                  "internalType": "uint256[2][2]",
                  "name": "b",
                  "type": "uint256[2][2]"
                },
                {
                  "internalType": "uint256[2]",
                  "name": "c",
                  "type": "uint256[2]"
                }
              ],
              "internalType": "struct Groth16Proof",
              "name": "proof",
              "type": "tuple"
            }
          ],
          "internalType": "struct LightClientRotate",
          "name": "update",
          "type": "tuple"
        }
      ],
      "name": "rotate",
      "outputs": [],
      "stateMutability": "nonpayable",
      "type": "function"
    },
    {
      "inputs": [
        {
          "components": [
            {
              "internalType": "uint256",
              "name": "attestedSlot",
              "type": "uint256"
            },
            {
              "internalType": "uint256",
              "name": "finalizedSlot",
              "type": "uint256"
            },
            {
              "internalType": "uint256",
              "name": "participation",
              "type": "uint256"
            },
            {
              "internalType": "bytes32",
              "name": "finalizedHeaderRoot",
              "type": "bytes32"
            },
            {
              "internalType": "bytes32",
              "name": "executionStateRoot",
              "type": "bytes32"
            },
            {
              "components": [
                {
                  "internalType": "uint256[2]",
                  "name": "a",
                  "type": "uint256[2]"
                },
                {
                  "internalType": "uint256[2][2]",
                  "name": "b",
                  "type": "uint256[2][2]"
                },
                {
                  "internalType": "uint256[2]",
                  "name": "c",
                  "type": "uint256[2]"
                }
              ],
              "internalType": "struct Groth16Proof",
              "name": "proof",
              "type": "tuple"
            }
          ],
          "internalType": "struct LightClientStep",
          "name": "update",
          "type": "tuple"
        }
      ],
      "name": "step",
      "outputs": [],
      "stateMutability": "nonpayable",
      "type": "function"
    },
    {
      "inputs": [
        {
          "internalType": "uint256",
          "name": "",
          "type": "uint256"
        }
      ],
      "name": "syncCommitteePoseidons",
      "outputs": [
        {
          "internalType": "bytes32",
          "name": "",
          "type": "bytes32"
        }
      ],
      "stateMutability": "view",
      "type": "function"
    },
    {
      "inputs": [
        {
          "internalType": "uint256",
          "name": "",
          "type": "uint256"
        }
      ],
      "name": "timestamps",
      "outputs": [
        {
          "internalType": "uint256",
          "name": "",
          "type": "uint256"
        }
      ],
      "stateMutability": "view",
      "type": "function"
    },
    {
      "inputs": [
        {
          "internalType": "uint256[2]",
          "name": "a",
          "type": "uint256[2]"
        },
        {
          "internalType": "uint256[2][2]",
          "name": "b",
          "type": "uint256[2][2]"
        },
        {
          "internalType": "uint256[2]",
          "name": "c",
          "type": "uint256[2]"
        },
        {
          "internalType": "uint256[65]",
          "name": "input",
          "type": "uint256[65]"
        }
      ],
      "name": "verifyProofRotate",
      "outputs": [
        {
          "internalType": "bool",
          "name": "r",
          "type": "bool"
        }
      ],
      "stateMutability": "view",
      "type": "function"
    },
    {
      "inputs": [
        {
          "internalType": "uint256[2]",
          "name": "a",
          "type": "uint256[2]"
        },
        {
          "internalType": "uint256[2][2]",
          "name": "b",
          "type": "uint256[2][2]"
        },
        {
          "internalType": "uint256[2]",
          "name": "c",
          "type": "uint256[2]"
        },
        {
          "internalType": "uint256[1]",
          "name": "input",
          "type": "uint256[1]"
        }
      ],
      "name": "verifyProofStep",
      "outputs": [
        {
          "internalType": "bool",
          "name": "r",
          "type": "bool"
        }
      ],
      "stateMutability": "view",
      "type": "function"
    }
  ]